scribelex/__init__.py
scribelex/base.py
scribelex/common.py
scribelex-1.0.11.dist-info/LICENSE
scribelex-1.0.11.dist-info/METADATA
scribelex-1.0.11.dist-info/WHEEL
scribelex-1.0.11.dist-info/top_level.txt
scribelex-1.0.11.dist-info/RECORD
